pywechatpay/__init__.py
pywechatpay/constants.py
pywechatpay/core.py
pywechatpay/exceptions.py
pywechatpay-0.1.0.dist-info/METADATA
pywechatpay-0.1.0.dist-info/WHEEL
pywechatpay-0.1.0.dist-info/top_level.txt
pywechatpay-0.1.0.dist-info/RECORD
