Metadata-Version: 2.1
Name: pywechatpay
Version: 0.1.0
Summary: Python SDK for WechatPay V3
Home-page: https://github.com/dust8/pywechatpay
Author: dust8
License: BSD
Keywords: python sdk wechatpay v3
Platform: UNKNOWN
Classifier: Development Status :: 3 - Alpha
Classifier: Topic :: Utilities
Classifier: License :: OSI Approved :: BSD License
Classifier: Programming Language :: Python :: 3.6
Classifier: Programming Language :: Python :: 3.7
Classifier: Programming Language :: Python :: 3.8
Classifier: Programming Language :: Python :: 3.9
Classifier: Programming Language :: Python :: 3.10
Requires-Dist: cryptography
Requires-Dist: requests
